dabox/__init__.py
dabox/env.py
dabox/assets/mediamtx.yml
dabox/assets/video_streams.mdx
dabox/gui/__init__.py
dabox/gui/__main__.py
dabox/gui/gui.py
dabox/gui/theme.py
dabox/inference/__init__.py
dabox/inference/__main__.py
dabox/inference/infer.py
dabox/inference/yolov8/__init__.py
dabox/inference/yolov8/yolov8.py
dabox/scripts/__init__.py
dabox/scripts/dabox_kill.py
dabox/scripts/dabox_up.py
dabox/scripts/preflight.py
dabox/streams/__init__.py
dabox/streams/mediamtx.py
dabox/util/__init__.py
dabox/util/cli_logo.py
dabox/util/devices.py
dabox/util/drawing.py
dabox/util/logging.py
dabox/util/projection.py
dabox/util/subprocess.py
dabox_project-0.1.2.dist-info/LICENSE
dabox_project-0.1.2.dist-info/METADATA
dabox_project-0.1.2.dist-info/WHEEL
dabox_project-0.1.2.dist-info/entry_points.txt
dabox_project-0.1.2.dist-info/top_level.txt
dabox_project-0.1.2.dist-info/RECORD
