Metadata-Version: 2.1
Name: dabox-project
Version: 0.1.2
Summary: The DABOX project
License: MIT
Project-URL: GitHub, https://github.com/jefequien/dabox
Classifier: Programming Language :: Python :: 3
Classifier: Programming Language :: Python :: 3.10
Classifier: Programming Language :: Python :: 3.11
Classifier: License :: OSI Approved :: MIT License
Classifier: Operating System :: OS Independent
Requires-Python: >=3.10
License-File: LICENSE
Requires-Dist: numpy
Requires-Dist: onnxruntime
Requires-Dist: opencv-python
Requires-Dist: rich
Requires-Dist: pyzmq
Requires-Dist: viser
Provides-Extra: dev
Requires-Dist: mypy ; extra == 'dev'
Requires-Dist: pre-commit ; extra == 'dev'
Requires-Dist: pytest ; extra == 'dev'
Requires-Dist: ruff ; extra == 'dev'
